MANIFEST.in
setup.cfg
setup.py
tw/__init__.py
tw.tabber.egg-info/PKG-INFO
tw.tabber.egg-info/SOURCES.txt
tw.tabber.egg-info/dependency_links.txt
tw.tabber.egg-info/entry_points.txt
tw.tabber.egg-info/namespace_packages.txt
tw.tabber.egg-info/not-zip-safe
tw.tabber.egg-info/requires.txt
tw.tabber.egg-info/top_level.txt
tw/tabber/__init__.py
tw/tabber/release.py
tw/tabber/static/tabber-minimized.js
tw/tabber/static/tabber.css
tw/tabber/static/tabber.js
tw/tabber/static/tabber_cookie.js