Metadata-Version: 1.0
Name: tw.tabber
Version: 0.8
Summary: Tabber ToscaWidget using BarelyFitz's tabber
Home-page: http://toscawidgets.org/
Author: Alberto Valverde Gonzalez
Author-email: alberto@toscat.net
License: UNKNOWN
Download-URL: http://toscawidgets.org/download
Keywords: toscawidgets.widgets
Platform: UNKNOWN
